odoo9_addon_pos_customer_required-9.0.1.0.0-py2.7-nspkg.pth
odoo_addons/pos_customer_required/__openerp__.py
odoo_addons/pos_customer_required/__init__.py
odoo_addons/pos_customer_required/README.rst
odoo_addons/pos_customer_required/migrations/9.0.1.0.0/pre-migration.py
odoo_addons/pos_customer_required/migrations/9.0.1.0.0/post-migration.py
odoo_addons/pos_customer_required/models/pos_make_payment.py
odoo_addons/pos_customer_required/models/__init__.py
odoo_addons/pos_customer_required/models/pos_order.py
odoo_addons/pos_customer_required/models/pos_config.py
odoo_addons/pos_customer_required/i18n/nl_NL.po
odoo_addons/pos_customer_required/i18n/fr.po
odoo_addons/pos_customer_required/views/pos_order_view.xml
odoo_addons/pos_customer_required/views/pos_config_view.xml
odoo_addons/pos_customer_required/tests/test_pos.py
odoo_addons/pos_customer_required/tests/__init__.py
odoo_addons/pos_customer_required/demo/pos_config.yml
odoo_addons/pos_customer_required/static/description/frontend_pos_error_message.png
odoo_addons/pos_customer_required/static/description/icon.png
odoo_addons/pos_customer_required/static/src/js/pos_customer_required.js
odoo_addons/pos_customer_required/static/src/xml/templates.xml
odoo9_addon_pos_customer_required-9.0.1.0.0.dist-info/top_level.txt
odoo9_addon_pos_customer_required-9.0.1.0.0.dist-info/WHEEL
odoo9_addon_pos_customer_required-9.0.1.0.0.dist-info/RECORD
odoo9_addon_pos_customer_required-9.0.1.0.0.dist-info/metadata.json
odoo9_addon_pos_customer_required-9.0.1.0.0.dist-info/DESCRIPTION.rst
odoo9_addon_pos_customer_required-9.0.1.0.0.dist-info/METADATA
odoo9_addon_pos_customer_required-9.0.1.0.0.dist-info/namespace_packages.txt
