Metadata-Version: 2.0
Name: odoo9-addon-pos-customer-required
Version: 9.0.1.0.0
Summary: Point of Sale Require Customer
Home-page: http://www.apertoso.be
Author: UNKNOWN
Author-email: UNKNOWN
License: UNKNOWN
Platform: UNKNOWN
Requires-Dist: odoo (<9.1a,>=9.0a)
Classifier: Programming Language :: Python :: 2.7
Classifier: Framework :: Odoo
